Changelog.rst
LICENSE
MANIFEST.in
Makefile
README.rst
setup.cfg
setup.py
docs/Makefile
docs/conf.py
docs/dbconn.rst
docs/index.rst
pgdbconn/__init__.py
pgdbconn/dbconn.py
pgdbconn/pycompat.py
pgdbconn.egg-info/PKG-INFO
pgdbconn.egg-info/SOURCES.txt
pgdbconn.egg-info/dependency_links.txt
pgdbconn.egg-info/requires.txt
pgdbconn.egg-info/top_level.txt
tests/test_pgdbconn.py