Metadata-Version: 1.1
Name: pgdbconn
Version: 0.8.0
Summary: Object-oriented layer over Psycopg2 to connect and interact with Postgres databases
Home-page: https://github.com/perseas/pgdbconn
Author: Joe Abbate
Author-email: jma@freedomcircle.com
License: BSD
Platform: OS-independent
Classifier: Development Status :: 4 - Beta
Classifier: Environment :: Console
Classifier: Intended Audience :: Developers
Classifier: Intended Audience :: Information Technology
Classifier: Intended Audience :: System Administrators
Classifier: License :: OSI Approved :: BSD License
Classifier: Natural Language :: English
Classifier: Operating System :: OS Independent
Classifier: Programming Language :: Python
Classifier: Programming Language :: Python :: 2
Classifier: Programming Language :: Python :: 2.7
Classifier: Programming Language :: Python :: 3
Classifier: Programming Language :: Python :: 3.4
Classifier: Programming Language :: Python :: 3.5
Classifier: Programming Language :: SQL
Classifier: Topic :: Database :: Front-Ends
